uwVIKOR/__init__.py
uwVIKOR/uwVIKOR.py
uwVIKOR-1.0.0.dist-info/METADATA
uwVIKOR-1.0.0.dist-info/WHEEL
uwVIKOR-1.0.0.dist-info/top_level.txt
uwVIKOR-1.0.0.dist-info/RECORD
