Metadata-Version: 2.1
Name: uwVIKOR
Version: 1.0.0
Summary: Unweighted VIKOR method
Home-page: https://github.com/Aaron-AALG/uwVIKOR
Download-URL: https://github.com/Aaron-AALG/uwVIKOR/releases/tag/uwVIKOR_1.0.0
Author: Aaron Lopez-Garcia
Author-email: logara8@alumni.uv.es
License: MIT
Classifier: Programming Language :: Python :: 3.8
Classifier: License :: OSI Approved :: MIT License
Requires-Dist: numpy >=1.19
Requires-Dist: scipy >=1.6.3
